{
  "Gravity": 1,
  "Waves": 0,
  "PointsToWin":1,
  "TextSpeed": 0.05,
  "DeathReset": false,
  "Actors": [
    {
      "Name": "Player",
      "HP": 80,
      "MoveSpeed": 10,
      "SprintSpeed": 2,
      "Weapon": "Rifle"
    },
    {
      "Name": "Amogus",
      "HP": 20,
      "MoveSpeed": 10,
      "SprintSpeed": 0.1,
      "SlowTurn": 0.95,
      "Weapon": "Pistol"
    },
    {
      "Name": "Gator",
      "HP": 30,
      "MoveSpeed": 12,
      "SprintSpeed": 0.1,
      "SlowTurn": 0.95,
      "Weapon": "Sword"
    },
    {
      "Name": "Eyeball",
      "HP": 40,
      "MoveSpeed": 17,
      "SprintSpeed": 0.1,
      "SlowTurn": 0.95,
      "Weapon": "pistol"
    }
  ],
  "Weapons": [
    {
      "Color":"Green",
      "Text": "Pistol",
      "Damage":25,
      "RateOfFire":0.5,
      "Accuracy":1,
      "Knockback":10
    },
    {
      "Color":"Blue",
      "Text": "Rifle",
      "Type": "Hitscan",
      "Damage": 10,
      "Ammo": 30,
      "RateOfFire":0.2
    },
    {
      "Color":"Red",
      "Text": "Rocket",
      "Damage": 10,
      "Ammo": 3,
      "RateOfFire":1,
      "Accuracy":2,
      "Speed":30,
      "ExplodeRadius":3,
      "ExplodeDamage":50,
      "SelfDamage":true,
      "Knockback":10
    },
    {
      "Color":"Pink",
      "Text": "Grenade",
      "Damage": 20,
      "Ammo": 10,
      "RateOfFire":0.5,
      "Accuracy":5,
      "Speed":20,
      "Gravity":2,
      "ExplodeRadius":2,
      "ExplodeDamage":20,
      "SelfDamage":true,
      "Knockback":1,
      "Bounce":2.5,
      "Lifetime":3,
      "Type":"Grenade"
    },
    {
      "Color":"Green",
      "Text": "Shotgun",
      "Damage": 5,
      "Ammo": 10,
      "RateOfFire":0.4,
      "Accuracy":15,
      "Shots":5
    },
    {
      "Color":"White",
      "Text": "Uzi",
      "Damage": 5,
      "Ammo": 90,
      "RateOfFire":0.1,
      "Accuracy":10
    },
    {
      "Color":"Orange",
      "Text": "Sword",
      "Damage": 25,
      "Ammo": 90,
      "RateOfFire":0.5,
      "Type": "Melee"
    },
    {
      "Color":"Orange",
      "Text": "Plasma Beam",
      "Type": "Beam",
      "Lifetime": 15,
      "Damage": 3,
      "RateOfFire":0.1
    },
    {
      "Color":"Orange",
      "Text": "Gravgun",
      "Type": "Gravgun",
      "Lifetime": 15,
      "Damage": 0.99
    }
  ],
  "Items":[
    {
      "Text": "1 Point",
      "Type": "Points",
      "Amount": 1,
      "Color": "Yellow"
    },
    {
      "Text": "Health",
      "Type": "Healing",
      "Amount": 50,
      "Color": "Green"
    }
  ]
}